CHANGES.rst
LICENSE.rst
MANIFEST.in
README.rst
setup.py
src/collective/__init__.py
src/collective.pfg.starrating.egg-info/PKG-INFO
src/collective.pfg.starrating.egg-info/SOURCES.txt
src/collective.pfg.starrating.egg-info/dependency_links.txt
src/collective.pfg.starrating.egg-info/entry_points.txt
src/collective.pfg.starrating.egg-info/namespace_packages.txt
src/collective.pfg.starrating.egg-info/not-zip-safe
src/collective.pfg.starrating.egg-info/requires.txt
src/collective.pfg.starrating.egg-info/top_level.txt
src/collective/pfg/__init__.py
src/collective/pfg/starrating/__init__.py
src/collective/pfg/starrating/config.py
src/collective/pfg/starrating/configure.zcml
src/collective/pfg/starrating/field.py
src/collective/pfg/starrating/profile/cssregistry.xml
src/collective/pfg/starrating/profile/factorytool.xml
src/collective/pfg/starrating/profile/jsregistry.xml
src/collective/pfg/starrating/profile/metadata.xml
src/collective/pfg/starrating/profile/skins.xml
src/collective/pfg/starrating/profile/types.xml
src/collective/pfg/starrating/profile/types/FormFolder.xml
src/collective/pfg/starrating/profile/types/FormStarRatingField.xml
src/collective/pfg/starrating/resources/pfgstarrating.js
src/collective/pfg/starrating/resources/star_icon.gif
src/collective/pfg/starrating/resources/jquery.rating/LICENSE
src/collective/pfg/starrating/resources/jquery.rating/README.markdown
src/collective/pfg/starrating/resources/jquery.rating/default.html
src/collective/pfg/starrating/resources/jquery.rating/jquery.rating.css
src/collective/pfg/starrating/resources/jquery.rating/jquery.rating.js
src/collective/pfg/starrating/resources/jquery.rating/project.tmproj
src/collective/pfg/starrating/resources/jquery.rating/star.gif
src/collective/pfg/starrating/resources/jquery.rating/js/jquery-1.6.1.min.js
src/collective/pfg/starrating/skins/starrating_atwidget/pfg_starrating.pt