Metadata-Version: 1.1
Name: collective.pfg.starrating
Version: 1.0
Summary: Star Rating Field for PloneFormGen
Home-page: UNKNOWN
Author: BlueDynamics Alliance
Author-email: dev@bluedynamics.com
License: GPLv2
Platform: UNKNOWN
Classifier: Development Status :: 5 - Production/Stable
Classifier: License :: OSI Approved :: GNU General Public License (GPL)
Classifier: Operating System :: OS Independent
Classifier: Programming Language :: Python
Classifier: Topic :: Software Development
Classifier: Framework :: Plone
